file_resubmit/admin.py
file_resubmit/__init__.py
file_resubmit/widgets.py
file_resubmit/cache.py
django_file_resubmit-0.5.1.dist-info/DESCRIPTION.rst
django_file_resubmit-0.5.1.dist-info/METADATA
django_file_resubmit-0.5.1.dist-info/metadata.json
django_file_resubmit-0.5.1.dist-info/WHEEL
django_file_resubmit-0.5.1.dist-info/top_level.txt
django_file_resubmit-0.5.1.dist-info/RECORD
tests/__init__.py
tests/test_all.py
tests/settings.py
