Metadata-Version: 2.0
Name: django-file-resubmit
Version: 0.5.1
Summary: Keeps submited files when validation errors occur.
Home-page: https://github.com/un1t/django-file-resubmit
Author: Ilya Shalyapin
Author-email: ishalyapin@gmail.com
License: MIT License
Download-URL: https://github.com/un1t/django-file-resubmit/tarball/master
Keywords: django form filefield resubmit
Platform: UNKNOWN
Classifier: Environment :: Web Environment
Classifier: Framework :: Django
Classifier: Intended Audience :: Developers
Classifier: Programming Language :: Python
Classifier: Programming Language :: Python :: 2
Classifier: Programming Language :: Python :: 2.7
Classifier: Programming Language :: Python :: 3
Classifier: Programming Language :: Python :: 3.4
Requires: python (>= 2.7)
Requires: django (>= 1.5)
